mgdlib/__init__.py
mgdlib/calculator.py
mgdlib-0.2.dist-info/LICENSE
mgdlib-0.2.dist-info/METADATA
mgdlib-0.2.dist-info/WHEEL
mgdlib-0.2.dist-info/top_level.txt
mgdlib-0.2.dist-info/RECORD
