Metadata-Version: 2.1
Name: mgdlib
Version: 0.2
Summary: Una libreria di esempio
Home-page: https://github.com
Author: MGDLab
Author-email: luca.santaniello.81@gmail.com
License: MIT
License-File: LICENSE
